{"data_mtime": 1589374930, "dep_lines": [122, 1, 1, 1], "dep_prios": [20, 5, 30, 30], "dependencies": ["pydatastructs.linear_data_structures.arrays", "builtins", "abc", "typing"], "hash": "e0b9d161b555c9ee7b11b51923084e0e73722fb260b58fe262556d6be8cc62f0", "id": "pydatastructs.utils.misc_util", "ignore_all": false, "interface_hash": "73e0a050ed2465ce50641b761a0ebcd08afd982d68b2ebc3034f2443b7d1c6d5", "mtime": 1589375516, "options": {"allow_redefinition": false, "allow_untyped_globals": false, "always_false": [], "always_true": [], "bazel": false, "check_untyped_defs": false, "disallow_any_decorated": false, "disallow_any_explicit": false, "disallow_any_expr": false, "disallow_any_generics": false, "disallow_any_unimported": false, "disallow_incomplete_defs": false, "disallow_subclassing_any": false, "disallow_untyped_calls": false, "disallow_untyped_decorators": false, "disallow_untyped_defs": false, "follow_imports": "silent", "follow_imports_for_stubs": false, "ignore_errors": false, "ignore_missing_imports": true, "implicit_reexport": true, "local_partial_types": false, "mypyc": false, "no_implicit_optional": false, "platform": "linux", "plugins": [], "show_none_errors": true, "strict_equality": false, "strict_optional": true, "strict_optional_whitelist": null, "warn_no_return": true, "warn_return_any": false, "warn_unreachable": false, "warn_unused_ignores": false}, "path": "/home/muskan/pydatastructs/pydatastructs/utils/misc_util.py", "plugin_data": null, "size": 10269, "suppressed": [], "version_id": "0.770"}